fixconf/__init__.py
fixconf/script.py
fixconf-0.0.1.dist-info/METADATA
fixconf-0.0.1.dist-info/WHEEL
fixconf-0.0.1.dist-info/top_level.txt
fixconf-0.0.1.dist-info/RECORD
